audiostream2py/__init__.py
audiostream2py/audio.py
audiostream2py-0.0.2.dist-info/LICENSE
audiostream2py-0.0.2.dist-info/METADATA
audiostream2py-0.0.2.dist-info/WHEEL
audiostream2py-0.0.2.dist-info/top_level.txt
audiostream2py-0.0.2.dist-info/RECORD
