Metadata-Version: 2.1
Name: audiostream2py
Version: 0.0.2
Summary: stream2py interface for audio
Home-page: https://github.com/i2mint/audiostream2py
Author: OtoSense
License: apache-2.0
Platform: any
